[{
    "title": "BST Bau GmbH",
    "slug": "bst-bau-gmbh",
    "url": "https://www.bst-bau.de/",
    "image": "./images/bst.jpeg",
    "description": "I built this to show off my sweet skills!"
}, {
    "title": "Bjöerk GmbH",
    "slug": "bjoerk-gmbh",
    "url": "https://www.bjoerk.de/",
    "image": "./images/bjoerk.jpeg",
    "description": "This one is also good."
}, {
    "title": "Bjöerk Movies",
    "slug": "bjoerk-movies",
    "url": "https://www.bjoerkmovies.de/",
    "image": "./images/bjoerk-movies.jpeg",
    "description": "This one is also good."
}]